{
  "latest_version": [
    "0.14.3"
  ],
  "meta": {
    "description": "API Wrapper and command line client forthe open-source note taking tool paperwork",
    "homepage": "https://github.com/ntnn/paperwrap",
    "license": "MIT"
  },
  "versions": [
    {
      "0.14.3": {
        "sha256": "50473a4b69f393338bab6c3b55c6d6cdba25a6c1320f82a44783fc5a94f1b9ff",
        "url": "https://files.pythonhosted.org/packages/14/a4/42c0e7162087228365870aeac83af2159dba2b1e892c38236222bf4e4f5f/paperwrap-0.14.3.tar.gz"
      }
    }
  ]
}