{
  "latest_version": [
    "0.1.1"
  ],
  "meta": {
    "description": "Django app with a template tag to allow you to include sparklines of the 52-week commit history for a project on Github",
    "homepage": "http://github.com/flother/participationgraphs",
    "license": "GPL"
  },
  "versions": [
    {
      "0.1.1": {
        "sha256": "05ce4954beca8e6db66f216edc74a6e8417fbfbd04d784e1d6f70c7b7583b5ce",
        "url": "https://files.pythonhosted.org/packages/4b/de/222dc9f74e474cd34f01b0d9fc78d528b98e4d85725cc176fff54bb46640/participationgraphs-0.1.1.tar.gz"
      }
    }
  ]
}