{
  "latest_version": [
    "2.0.5"
  ],
  "meta": {
    "description": "A sphinx theme I use for most projects. Derivative of Eli Collins's cloud_sptheme",
    "homepage": "https://github.com/peter1000/PSphinxTheme",
    "license": "BSD-3-Clause"
  },
  "versions": [
    {
      "2.0.5": {
        "sha256": "a908bafacce75b78b396bfa8a85353550987e38661ddbe95e538359bd8e78542",
        "url": "https://files.pythonhosted.org/packages/9c/c3/ef591d625532110a7ca544cc24e89422242836247f24da75f94f85d46dd7/PSphinxTheme-2.0.5.tar.bz2"
      }
    }
  ]
}