{
  "latest_version": [
    "1.0rc1"
  ],
  "meta": {
    "description": "Backport of new features in Python's tempfile module",
    "homepage": "https://github.com/pjdelport/backports.tempfile",
    "license": "Python Software Foundation License"
  },
  "versions": [
    {
      "1.0rc1": {
        "sha256": "1492e2fd8e8abcae6a9c9e78edc52aae4234937c5d462fd3ce0e29c1a4687d3b",
        "url": "https://files.pythonhosted.org/packages/d6/68/49955c14c22b73e5a0eb2e08d431f031e7ce226b2d29894f891bade22e82/backports.tempfile-1.0rc1.tar.gz"
      }
    }
  ]
}