{
  "latest_version": [
    "0.0.2"
  ],
  "meta": {
    "description": "bit foundation android_ndk zc.buildout recipe",
    "homepage": "http://www.python.org/pypi/bit.recipe.android_ndk",
    "license": "GPL"
  },
  "versions": [
    {
      "0.0.2": {
        "sha256": "26824aa92041f442a9ba91f69fbff18010404c3013e3e590d99ba50b374ac6d5",
        "url": "https://files.pythonhosted.org/packages/7c/04/9371df8715ade3d58a1755d4b66489a1d44f723918dc4e2179af6e4f647d/bit.recipe.android_ndk-0.0.2.zip"
      }
    }
  ]
}