{
  "latest_version": [
    "0.2"
  ],
  "meta": {
    "description": "Eagle is an abstraction layer atop Graphical Toolkits focused on\nmaking simple applications easy to build while powerful in features",
    "homepage": "http://code.gustavobarbieri.com.br/eagle/",
    "license": "LGPL"
  },
  "versions": {
    "0.2": {
      "sha256": "7af5dffd0f1f2b5c46dcc19f5b5a47e96dc3ce387f1de05199df249e8d2bed59",
      "url": "https://files.pythonhosted.org/packages/dd/5c/4318a37b78339ab35e8340d51ddcb76f8005261dffcd5d1e9ab7cec0b5cd/eagle-0.2.tar.gz"
    }
  }
}