{
  "latest_version": [
    "0.9"
  ],
  "meta": {
    "description": "Provides less than (lt) and greater than (gt) queries to TiddlyWeb for date and float fields",
    "homepage": "http://pypi.python.org/pypi/tiddlywebplugins.ltgt"
  },
  "versions": [
    {
      "0.9": {
        "sha256": "8a773567b20358fcdab055bb54d836a625f79914dd44b9e9e3094d61c93df46f",
        "url": "https://files.pythonhosted.org/packages/ab/88/089e2d854b8564528b9c8f4cb76263d4963f437181151b5468ddc2063f5f/tiddlywebplugins.ltgt-0.9.tar.gz"
      }
    }
  ]
}