{
  "latest_version": [
    "0.1"
  ],
  "meta": {
    "description": "Python Client for accessing the Tumblr API",
    "homepage": "https://github.com/medecau/tumblr-python",
    "license": "Apache License, Version 2.0"
  },
  "versions": [
    {
      "0.1": {
        "sha256": "cf941af6c515e185977882d0c01aa0873102e308b4b5493be13c62e43fdbbb04",
        "url": "https://files.pythonhosted.org/packages/65/30/b84ad226ff32ac50645c30658c8ab4c7ee8b26e22800dc9ebc43c7ae94a2/tumblr2-0.1.tar.gz"
      }
    }
  ]
}