{
  "latest_version": [
    "0.1a1"
  ],
  "meta": {
    "description": "An environment and API that simplifies workingwith multiple SSH servers in an asynchronous way",
    "homepage": "http://www.conchoctopus.org",
    "license": "MIT"
  },
  "versions": [
    {
      "0.1a1": {
        "sha256": "890585396c2c253a7e07e04c555e06ba1e09b85c2a182ba2dd26a4fd189bdf8e",
        "url": "https://files.pythonhosted.org/packages/19/ce/ef13379bdac9ef7cf14f21e40df3d447a62bd6dc79be930e587d939c29ca/conchoctopus-0.1a1.tar.gz"
      }
    }
  ]
}