{
  "latest_version": [
    "1.0"
  ],
  "meta": {
    "description": "A Coopr package for modeling bilevel programs",
    "homepage": "https://software.sandia.gov/svn/public/coopr/coopr.bilevel",
    "license": "BSD"
  },
  "versions": [
    {
      "1.0": {
        "sha256": "5e6029cecd3e6085cc684aaed8206ea4521a6def1bbb114be231cbeda28e5506",
        "url": "https://files.pythonhosted.org/packages/ff/4a/b64e5d03ec67e62676acdcb6dccea99380a42aa7cc77d13fca13def2f6de/coopr.bilevel-1.0.tar.gz"
      }
    }
  ]
}